src/random_digit.v
// Copyright 2025 Michael Schurz
//
// Licensed under the Apache License, Version 2.0 (the "License");
// you may not use this file except in compliance with the License.
// You may obtain a copy of the License at
//
// http://www.apache.org/licenses/LICENSE−2.0
//
// Unless required by applicable law or agreed to in writing, software
// distributed under the License is distributed on an "AS IS" BASIS,
// WITHOUT WARRANTIES OR CONDITIONS OF ANY KIND, either express or implied.
// See the License for the specific language governing permissions and
// limitations under the License.

`timescale 1ns / 1ps

module random_digit (
    input wire clk,
    input wire reset,
    output reg [3:0] rnd  //0–9
);
    reg [3:0] lfsr = 4'b1010;
	wire feedback = lfsr[3] ^ lfsr[2];

    always @(posedge clk or posedge reset) begin
        if (reset) begin
            lfsr <= 4'b1010;
        end else begin
            lfsr <= {lfsr[2:0], feedback};
        end
    end

    always @(posedge clk) begin
        if (lfsr[3:0] < 4'd10)
            rnd <= lfsr;
        else
            rnd <= lfsr - 4'd10;  // wrap um 10
    end
endmodule

src/random_digit_tb.v
`timescale 1ns/1ps

`include "random_digit.v"

module random_digit_tb;
    reg clk = 1'b0;
    reg reset = 1'b1;
    wire [3:0] rnd;

    // Instantiation
    random_digit uut (
        .clk(clk),
        .reset(reset),
        .rnd(rnd)
    );

    always #10 clk = ~clk;

    initial begin
    	$dumpfile("random_digit_tb.vcd");
    	$dumpvars;
    	
    	#50 reset = 1'b0;
    	
        #1000 $finish;
    end

    // output
    initial begin
        $monitor("Zeit = %0t, Zufallszahl = %d", $time, rnd);
    end
endmodule

src/random_digit_tb.vcd
$date
	Sun Nov  9 01:29:34 2025
$end
$version
	Icarus Verilog
$end
$timescale
	1ps
$end
$scope module random_digit_tb $end
$var wire 4 ! rnd [3:0] $end
$var reg 1 " clk $end
$var reg 1 # reset $end
$scope module uut $end
$var wire 1 " clk $end
$var wire 1 $ feedback $end
$var wire 1 # reset $end
$var reg 4 % lfsr [3:0] $end
$var reg 4 & rnd [3:0] $end
$upscope $end
$upscope $end
$enddefinitions $end
$comment Show the parameter values. $end
$dumpall
$end
#0
$dumpvars
bx &
b1010 %
1$
1#
0"
bx !
$end
#10000
b0 !
b0 &
1"
#20000
0"
#30000
1"
#40000
0"
#50000
b101 %
1"
0#
#60000
0"
#70000
b101 !
b101 &
b1011 %
1"
#80000
0"
#90000
b1 !
b1 &
b111 %
1"
#100000
0"
#110000
0$
b111 !
b111 &
b1111 %
1"
#120000
0"
#130000
b101 !
b101 &
b1110 %
1"
#140000
0"
#150000
b100 !
b100 &
b1100 %
1"
#160000
0"
#170000
1$
b10 !
b10 &
b1000 %
1"
#180000
0"
#190000
0$
b1000 !
b1000 &
b1 %
1"
#200000
0"
#210000
b1 !
b1 &
b10 %
1"
#220000
0"
#230000
1$
b10 !
b10 &
b100 %
1"
#240000
0"
#250000
b100 !
b100 &
b1001 %
1"
#260000
0"
#270000
0$
b1001 !
b1001 &
b11 %
1"
#280000
0"
#290000
1$
b11 !
b11 &
b110 %
1"
#300000
0"
#310000
0$
b110 !
b110 &
b1101 %
1"
#320000
0"
#330000
1$
b11 !
b11 &
b1010 %
1"
#340000
0"
#350000
b0 !
b0 &
b101 %
1"
#360000
0"
#370000
b101 !
b101 &
b1011 %
1"
#380000
0"
#390000
b1 !
b1 &
b111 %
1"
#400000
0"
#410000
0$
b111 !
b111 &
b1111 %
1"
#420000
0"
#430000
b101 !
b101 &
b1110 %
1"
#440000
0"
#450000
b100 !
b100 &
b1100 %
1"
#460000
0"
#470000
1$
b10 !
b10 &
b1000 %
1"
#480000
0"
#490000
0$
b1000 !
b1000 &
b1 %
1"
#500000
0"
#510000
b1 !
b1 &
b10 %
1"
#520000
0"
#530000
1$
b10 !
b10 &
b100 %
1"
#540000
0"
#550000
b100 !
b100 &
b1001 %
1"
#560000
0"
#570000
0$
b1001 !
b1001 &
b11 %
1"
#580000
0"
#590000
1$
b11 !
b11 &
b110 %
1"
#600000
0"
#610000
0$
b110 !
b110 &
b1101 %
1"
#620000
0"
#630000
1$
b11 !
b11 &
b1010 %
1"
#640000
0"
#650000
b0 !
b0 &
b101 %
1"
#660000
0"
#670000
b101 !
b101 &
b1011 %
1"
#680000
0"
#690000
b1 !
b1 &
b111 %
1"
#700000
0"
#710000
0$
b111 !
b111 &
b1111 %
1"
#720000
0"
#730000
b101 !
b101 &
b1110 %
1"
#740000
0"
#750000
b100 !
b100 &
b1100 %
1"
#760000
0"
#770000
1$
b10 !
b10 &
b1000 %
1"
#780000
0"
#790000
0$
b1000 !
b1000 &
b1 %
1"
#800000
0"
#810000
b1 !
b1 &
b10 %
1"
#820000
0"
#830000
1$
b10 !
b10 &
b100 %
1"
#840000
0"
#850000
b100 !
b100 &
b1001 %
1"
#860000
0"
#870000
0$
b1001 !
b1001 &
b11 %
1"
#880000
0"
#890000
1$
b11 !
b11 &
b110 %
1"
#900000
0"
#910000
0$
b110 !
b110 &
b1101 %
1"
#920000
0"
#930000
1$
b11 !
b11 &
b1010 %
1"
#940000
0"
#950000
b0 !
b0 &
b101 %
1"
#960000
0"
#970000
b101 !
b101 &
b1011 %
1"
#980000
0"
#990000
b1 !
b1 &
b111 %
1"
#1000000
0"
#1010000
0$
b111 !
b111 &
b1111 %
1"
#1020000
0"
#1030000
b101 !
b101 &
b1110 %
1"
#1040000
0"
#1050000
b100 !
b100 &
b1100 %
1"
